cuisel/__init__.py
cuisel/_cuisel.py
cuisel/cli.py
cuisel/controller.py
cuisel/viewer.py
cuisel-1.0.0.dist-info/LICENSE
cuisel-1.0.0.dist-info/METADATA
cuisel-1.0.0.dist-info/WHEEL
cuisel-1.0.0.dist-info/entry_points.txt
cuisel-1.0.0.dist-info/top_level.txt
cuisel-1.0.0.dist-info/RECORD
